xia_fields_scw/__init__.py
xia_fields_scw/fields.cp39-win_amd64.pyd
xia_fields_scw-0.0.1.dist-info/LICENSE.txt
xia_fields_scw-0.0.1.dist-info/METADATA
xia_fields_scw-0.0.1.dist-info/WHEEL
xia_fields_scw-0.0.1.dist-info/top_level.txt
xia_fields_scw-0.0.1.dist-info/RECORD
