Metadata-Version: 2.1
Name: xia-fields-scw
Version: 0.0.1
Summary: X-I-A
Home-page: https://develop.x-i-a.com/docs/xia-fields-scw/0.0.1/index.html
Author: X-I-A
Author-email: admin@x-i-a.com
License: UNKNOWN
Platform: UNKNOWN
Requires-Python: >=3.9
License-File: LICENSE.txt
Requires-Dist: xia-fields
